{
    "name": "Cpptest",
    "description": "Unit testing framework handling automated tests in C++",
    "url": "https://downloads.sourceforge.net/project/cpptest/cpptest/cpptest-1.1.2/cpptest-1.1.2.tar.gz",
    "mirror": null,
    "homepage": "https://cpptest.sourceforge.io/",
    "depends": [],
    "resource": [],
    "conflicts": [],
    "patches": [],
    "install": [
        "system \"./configure\", \"--disable-dependency-tracking\",",
        "\"--prefix=#{prefix}\"",
        "system \"make\", \"install\""
    ],
    "version": "1.1.2"
}