{
    "name": "GitSecret",
    "description": "Bash-tool to store the private data inside a git repo",
    "url": "https://github.com/sobolevn/git-secret/archive/v0.2.5.tar.gz",
    "mirror": null,
    "homepage": "https://sobolevn.github.io/git-secret/",
    "depends": [
        {
            "depend": "gawk",
            "build-depend": false
        },
        {
            "depend": "gnupg",
            "build-depend": false
        }
    ],
    "resource": [],
    "conflicts": [],
    "patches": [],
    "install": [
        "system \"make\", \"build\"",
        "system \"bash\", \"utils/install.sh\", prefix"
    ],
    "version": "0.2.5"
}