{
    "name": "Monkeysphere",
    "description": "Use the OpenPGP web of trust to verify ssh connections",
    "url": "https://mirrors.ocf.berkeley.edu/debian/pool/main/m/monkeysphere/monkeysphere_0.41.orig.tar.gz",
    "mirror": "https://mirrorservice.org/sites/ftp.debian.org/debian/pool/main/m/monkeysphere/monkeysphere_0.41.orig.tar.gz",
    "homepage": "https://web.monkeysphere.info/",
    "depends": [
        {
            "depend": "gnu-sed",
            "build-depend": true
        },
        {
            "depend": "libassuan",
            "build-depend": false
        },
        {
            "depend": "libgcrypt",
            "build-depend": false
        },
        {
            "depend": "libgpg-error",
            "build-depend": false
        },
        {
            "depend": "openssl",
            "build-depend": false
        }
    ],
    "resource": [
        {
            "name": "Crypt::OpenSSL::Bignum",
            "url": "https://cpan.metacpan.org/authors/id/K/KM/KMX/Crypt-OpenSSL-Bignum-0.06.tar.gz"
        }
    ],
    "conflicts": [],
    "patches": [],
    "install": [
        "ENV.prepend_path \"PATH\", Formula[\"gnu-sed\"].libexec/\"gnubin\"",
        "ENV.prepend_create_path \"PERL5LIB\", libexec/\"lib/perl5\"",
        "resource(\"Crypt::OpenSSL::Bignum\").stage do",
        "system \"perl\", \"Makefile.PL\", \"INSTALL_BASE=#{libexec}\"",
        "system \"make\", \"install\""
    ],
    "version": "0.41"
}